{
  "article": 242,
  "title": "Coorg",
  "text": "(1) Until Parliament by law otherwise provides, the constitution, powers and functions of the Coorg Legislative Council shall be the same as they were immediately before the commencement of this Constitution.\n⁠(2) The arrangements with respect to revenues collected in Coorg and expenses in respect of Coorg shall, until other provision is made in that behalf by the President by order, continue unchanged.\nWe are a not-for-profit initiative. Your support is crucial to help us grow and maintain our commitment to providing free and open access constitutional educational resources.\nSUPPORT US\n© 2025 Centre for Law and Policy Research Trust. All Rights Reserved.\nAbout Us\nBlog\nEvents\nSubscribe\nPrivacy Policy",
  "source": "constitutionofindia.net",
  "url": "https://www.constitutionofindia.net/articles/article-242",
  "source_type": "constitution",
  "jurisdiction": "India",
  "version": "Constitution of India, 1950"
}