{
  "article": 168,
  "title": "Constitution of Legislatures in States",
  "text": "(1) For every State there shall be a Legislature which shall consist of the Governor, and\n(a) in the States of Bihar, Bombay, Madras, Punjab, the United Provinces and West Bengal, two Houses;\n(b) in other States, one House.\n⁠(2) Where there are two Houses of the Legislature of a State, one shall be known as the Legislative Council and the other as the Legislative Assembly, and where there is only one House, it shall be known as the Legislative Assembly.",
  "source": "constitutionofindia.net",
  "url": "https://www.constitutionofindia.net/articles/article-168",
  "source_type": "constitution",
  "jurisdiction": "India",
  "version": "Constitution of India, 1950"
}