{
  "article": 5,
  "title": "Citizenship at the commencement of the Constitution",
  "text": "At the commencement of this Constitution, every person who has his domicile in the territory of India and —\n(a) who was born in the territory of India; or\n(b) either of whose parents was born in the territory of India; or\n(c) who has been ordinarily resident in the territory of India for not less than five years immediately preceding such commencement,\nshall be a citizen of India.",
  "source": "constitutionofindia.net",
  "url": "https://www.constitutionofindia.net/articles/article-5",
  "source_type": "constitution",
  "jurisdiction": "India",
  "version": "Constitution of India, 1950"
}