{
  "article": 335,
  "title": "Claims of Scheduled Castes and Scheduled Tribes to services and posts",
  "text": "The claims of the members of the Scheduled Castes and the Scheduled Tribes shall be taken into consideration, consistently with the maintenance of efficiency of administration, in the making of appointments to services and posts in connection with the affairs of the Union or of a State.\nSUMMARY",
  "source": "constitutionofindia.net",
  "url": "https://www.constitutionofindia.net/articles/article-335",
  "source_type": "constitution",
  "jurisdiction": "India",
  "version": "Constitution of India, 1950"
}