{
  "article": 180,
  "title": "Power of the Deputy Speaker or other person to perform the duties of the office of, or to act as, Speaker",
  "text": "(1) While the office of Speaker is vacant, the duties of the office shall be performed by the Deputy Speaker or, if the office of Deputy Speaker is also vacant, by such member of the Assembly as the Governor may appoint for the purpose.\n⁠(2) During the absence of the Speaker from any sitting of the Assembly the Deputy Speaker or, if he is also absent, such person as may be determined by the rules of procedure of the Assembly, or, if no such person is present, such other person as may be determined by the Assembly, shall act as Speaker.",
  "source": "constitutionofindia.net",
  "url": "https://www.constitutionofindia.net/articles/article-180",
  "source_type": "constitution",
  "jurisdiction": "India",
  "version": "Constitution of India, 1950"
}